{
  "slug": "sun-cleric",
  "spec": "Blessings",
  "id": "Sun Cleric Blessings SPEC",
  "name": "sun-cleric-blessings-spec",
  "global": { "barWidth": 250, "iconSize": 26, "secIconSize": 24, "procSize": 30, "gap": 3 },
  "stack": [
    { "kind": "buffRow", "icons": [
      { "label": "Holy Form", "indicator": "Holy Form",
        "lowPowerGlow": { "pct": 25, "powerType": 0, "color": [1, 0.82, 0.1, 1], "glowType": "buttonOverlay" } }
    ] },
    { "kind": "cdRow", "icons": [
      { "label": "Blessing of Absolution", "spell": 804249 },
      { "label": "Horusath Blast", "spell": 500154 },
      { "label": "Blessing of Triumph", "spell": 804250 },
      { "label": "Solar Invigoration", "spell": 806123 },
      { "label": "Blessing of Purity", "spell": 804253 },
      { "label": "Blessing of Retribution", "spell": 804254 },
      { "label": "Glare", "spell": 805583 },
      { "label": "Radiance", "spell": 800054 }
    ] },
    { "kind": "powerBar", "powerType": 0, "hi": [0.3, 0.55, 1, 1], "lo": [0.05, 0.12, 0.45, 1], "bg": [0.03, 0.05, 0.14, 0.85] },
    { "kind": "healthBar", "hi": [0.9, 0.16, 0.12, 1], "lo": [0.33, 0.02, 0.02, 1] },
    { "kind": "cdRow", "secondary": true, "icons": [
      { "label": "Holy Form", "spell": 805301 },
      { "label": "Solar Invocation Resplendence", "spell": 806159 },
      { "label": "Solar Invocation Conquest", "spell": 800764 },
      { "label": "Solar Prayer", "spell": 806479 },
      { "label": "New Day", "spell": 800600 }
    ] }
  ]
}
